eventhub_analyzer/__init__.py
eventhub_analyzer/main.py
eventhub_analyzer-0.6.1.dist-info/entry_points.txt
eventhub_analyzer-0.6.1.dist-info/WHEEL
eventhub_analyzer-0.6.1.dist-info/METADATA
eventhub_analyzer-0.6.1.dist-info/RECORD
