Metadata-Version: 2.1
Name: eventhub-analyzer
Version: 0.6.1
Summary: 
Home-page: https://github.com/deviceinsight/eventhub-analyzer
Author: Stefan Hudelmaier
Author-email: stefan.hudelmaier@device-insight.com
Requires-Python: >=3.10,<4.0
Classifier: Programming Language :: Python :: 3
Classifier: Programming Language :: Python :: 3.10
Classifier: Programming Language :: Python :: 3.11
Requires-Dist: azure-eventhub (>=5.11.1,<6.0.0)
Requires-Dist: azure-storage-blob (>=12.14.1,<13.0.0)
Requires-Dist: click (>=8.1.3,<9.0.0)
Requires-Dist: jsonpickle (>=3.0.1,<4.0.0)
Requires-Dist: python-dotenv (>=0.21.1,<0.22.0)
Requires-Dist: texttable (>=1.6.7,<2.0.0)
Project-URL: Repository, https://github.com/deviceinsight/eventhub-analyzer
